project_ai_mcp/__init__.py
project_ai_mcp/__main__.py
project_ai_mcp/config.py
project_ai_mcp/server.py
project_ai_mcp-0.1.2.dist-info/licenses/LICENSE
project_ai_mcp-0.1.2.dist-info/METADATA
project_ai_mcp-0.1.2.dist-info/WHEEL
project_ai_mcp-0.1.2.dist-info/entry_points.txt
project_ai_mcp-0.1.2.dist-info/top_level.txt
project_ai_mcp-0.1.2.dist-info/RECORD
