Metadata-Version: 2.4
Name: project-ai-mcp
Version: 0.1.2
Summary: A Model Context Protocol (MCP) server for Project AI
Author: philoveritas
License-Expression: MIT
Keywords: mcp,project-ai
Classifier: Development Status :: 3 - Alpha
Classifier: Intended Audience :: Developers
Classifier: Operating System :: OS Independent
Classifier: Programming Language :: Python :: 3
Classifier: Programming Language :: Python :: 3.12
Classifier: Topic :: Communications :: Chat
Classifier: Topic :: Software Development :: Libraries :: Python Modules
Requires-Python: >=3.12
License-File: LICENSE
Requires-Dist: mcp[cli]>=1.13.1
Requires-Dist: requests>=2.32.5
Dynamic: license-file
